localstack/sdk/clients.py
localstack/sdk/version.py
localstack/sdk/aws/__init__.py
localstack/sdk/aws/client.py
localstack/sdk/chaos/__init__.py
localstack/sdk/chaos/client.py
localstack/sdk/chaos/managers.py
localstack/sdk/pods/__init__.py
localstack/sdk/pods/client.py
localstack/sdk/pods/exceptions.py
localstack/sdk/state/__init__.py
localstack/sdk/state/client.py
localstack/sdk/testing/__init__.py
localstack/sdk/testing/decorators.py
localstack/sdk/testing/pytest/__init__.py
localstack/sdk/testing/pytest/plugins.py
localstack_sdk_python-4.12.0.dist-info/licenses/LICENSE.txt
localstack_sdk_python-4.12.0.dist-info/METADATA
localstack_sdk_python-4.12.0.dist-info/WHEEL
localstack_sdk_python-4.12.0.dist-info/entry_points.txt
localstack_sdk_python-4.12.0.dist-info/top_level.txt
localstack_sdk_python-4.12.0.dist-info/RECORD
