Metadata-Version: 2.4
Name: localstack-sdk-python
Version: 4.12.0
Summary: Python SDK for LocalStack
Author-email: LocalStack Team <info@localstack.cloud>
Project-URL: Homepage, https://localstack.cloud
Project-URL: Documentation, https://docs.localstack.cloud
Project-URL: Repository, https://github.com/localstack/localstack-sdk-python.git
Project-URL: Issues, https://github.com/localstack/localstack-sdk-python/issues
License-File: LICENSE.txt
Requires-Dist: localstack-sdk-generated
Dynamic: license-file
